dataiku_cli_requests/__init__.py
dataiku_cli_requests/dataiku_cli_requests.py
dataiku_cli_requests-1.0.dist-info/METADATA
dataiku_cli_requests-1.0.dist-info/WHEEL
dataiku_cli_requests-1.0.dist-info/entry_points.txt
dataiku_cli_requests-1.0.dist-info/top_level.txt
dataiku_cli_requests-1.0.dist-info/RECORD
